ugs3client
